<?xml version="1.0" encoding="UTF-8"?>
<metadata xml:lang="en"><Esri><CreaDate>20240502</CreaDate><CreaTime>17251800</CreaTime><ArcGISFormat>1.0</ArcGISFormat><SyncOnce>TRUE</SyncOnce><DataProperties><lineage><Process ToolSource="c:\program files (x86)\arcgis\desktop10.8\ArcToolbox\Toolboxes\Conversion Tools.tbx\ExportCAD" Date="20240502" Time="172518">ExportCAD contour1m DWG_R2018 C:\Users\STANDARD.UPENDRA-PC\Downloads\cell_at-main\nongpoh\contour1m.dwg Ignore_Filenames_in_Tables Overwrite_Existing_Files #</Process></lineage></DataProperties></Esri></metadata>
